colorizexl/__init__.py
colorizexl/colorizexl.py
colorizexl-0.2.1.data/data/data/boy.png
colorizexl-0.2.1.data/data/data/boy_annotated.png
colorizexl-0.2.1.data/data/data/chair.png
colorizexl-0.2.1.data/data/data/chair_annotated.png
colorizexl-0.2.1.dist-info/LICENSE
colorizexl-0.2.1.dist-info/METADATA
colorizexl-0.2.1.dist-info/WHEEL
colorizexl-0.2.1.dist-info/top_level.txt
colorizexl-0.2.1.dist-info/RECORD
